Metadata-Version: 1.0
Name: xadmind3
Version: 0.0.1
Summary: xadmin fit django3
Home-page: https://github.com/wychmod/xadmind3
Author: wychmod
Author-email: 17376512950@163.com
License: UNKNOWN
Platform: UNKNOWN
